malesmo/__init__.py
malesmo/combine/__init__.py
malesmo/combine/model_duals.py
malesmo/gboost/__init__.py
malesmo/gboost/model_catb.py
malesmo/gboost/model_dualb.py
malesmo/gboost/model_xgb.py
MaLeSMo-0.2.7.dist-info/LICENSE
MaLeSMo-0.2.7.dist-info/METADATA
MaLeSMo-0.2.7.dist-info/WHEEL
MaLeSMo-0.2.7.dist-info/entry_points.txt
MaLeSMo-0.2.7.dist-info/top_level.txt
MaLeSMo-0.2.7.dist-info/RECORD
